MANIFEST.in
README.md
mcdict.py
setup.cfg
setup.py
mcdict.egg-info/PKG-INFO
mcdict.egg-info/SOURCES.txt
mcdict.egg-info/dependency_links.txt
mcdict.egg-info/top_level.txt