Metadata-Version: 1.0
Name: mcdict
Version: 1.03
Summary: Enhance Python memcached client with a dictionary class
Home-page: https://github.com/wavetossed/mcdict
Author: Michael Dillon
Author-email: wavetossed@gmail.com
License: UNKNOWN
Download-URL: https://github.com/wavetossed/mcdict/tarball/master
Platform: UNKNOWN
Classifier: Development Status :: 4 - Beta
Classifier: Intended Audience :: Developers
Classifier: License :: OSI Approved :: MIT License
Classifier: Operating System :: OS Independent
Classifier: Programming Language :: Python
Classifier: Programming Language :: Python :: 2
Classifier: Topic :: Database :: Front-Ends
Classifier: Topic :: System :: Distributed Computing
Classifier: Topic :: Internet
Classifier: Topic :: Software Development :: Libraries :: Python Modules
